{
    "listen_port": 5002,
    "queues": {
        "encode": {
            "station_config": {
                "local_save": "/localbackup/tmp",
                "extensions": ["ogv", "ogg"],
                "server": "10.4.4.3",
                "base-folder": "/srv/av/cut/"
            },
            "base_path": "/home/av/eventstreamr/queue/encode/",
            "file_pattern": "*.json",
            "poll_length": 10
        },
        "cut": {
            "station_config": {
                "base-folder": "/srv/av/cut/"
            },
            "duplicate_complete": ""
            "base_path": "/home/av/eventstreamr/queue/cut/",
            "file_pattern": "*.json",
            "poll_length": 10
        }
    }
}
